fruitstand/Fruitstand.py
fruitstand/__init__.py
fruitstand/cli.py
fruitstand/controllers/baseline.py
fruitstand/controllers/main.py
fruitstand/controllers/test.py
fruitstand/factories/embeddings_factory.py
fruitstand/factories/llm_factory.py
fruitstand/schemas/baseline_schema.py
fruitstand/schemas/generate_baseline_schema.py
fruitstand/schemas/test_data_schema.py
fruitstand/services/embeddings/EmbeddingsService.py
fruitstand/services/embeddings/GeminiEmbeddings.py
fruitstand/services/embeddings/OpenAIEmbeddings.py
fruitstand/services/llms/AnthropicService.py
fruitstand/services/llms/GeminiService.py
fruitstand/services/llms/LLMService.py
fruitstand/services/llms/OpenAIService.py
fruitstand/utils/argument_utils.py
fruitstand/utils/file_utils.py
fruitstand/utils/vector_utils.py
fruitstand-0.15.0.dist-info/LICENSE
fruitstand-0.15.0.dist-info/METADATA
fruitstand-0.15.0.dist-info/WHEEL
fruitstand-0.15.0.dist-info/entry_points.txt
fruitstand-0.15.0.dist-info/RECORD
