Metadata-Version: 2.3
Name: fruitstand
Version: 0.15.0
Summary: A library for regression testing llm prompts
Author: gareth@deckarddesigns.com
Requires-Python: >=3.11,<4
Classifier: Programming Language :: Python :: 3
Classifier: Programming Language :: Python :: 3.11
Classifier: Programming Language :: Python :: 3.12
Classifier: Programming Language :: Python :: 3.13
Requires-Dist: anthropic (>=0.43.0,<0.44.0)
Requires-Dist: argparse (>=1.4.0,<2.0.0)
Requires-Dist: google-generativeai (>=0.8.3,<0.9.0)
Requires-Dist: numpy (>=2.2.1,<3.0.0)
Requires-Dist: openai (>=1.59.6,<2.0.0)
